recur_command/__init__.py
recur_command/__main__.py
recur_command/main.py
recur_command/py.typed
recur_command-0.5.0.dist-info/METADATA
recur_command-0.5.0.dist-info/WHEEL
recur_command-0.5.0.dist-info/entry_points.txt
recur_command-0.5.0.dist-info/licenses/LICENSE
recur_command-0.5.0.dist-info/RECORD
