Metadata-Version: 2.3
Name: recur-command
Version: 0.5.0
Summary: Retry a command with exponential backoff and jitter.
Author-email: "D. Bohdan" <dbohdan@dbohdan.com>
License-Expression: MIT
License-File: LICENSE
Keywords: retry
Classifier: Development Status :: 3 - Alpha
Classifier: Environment :: Console
Classifier: License :: OSI Approved :: MIT License
Classifier: Operating System :: MacOS :: MacOS X
Classifier: Operating System :: Microsoft :: Windows
Classifier: Operating System :: POSIX
Classifier: Programming Language :: Python :: 3
Classifier: Topic :: Utilities
Requires-Python: >=3.9
Requires-Dist: simpleeval==1.*
